{
"skeleton": {
	"hash": "IxlrL/BG/5kcDtFp+YgjvDGBmqw",
	"spine": "3.8.99",
	"x": -245.2,
	"y": -122.78,
	"width": 481.64,
	"height": 308.66,
	"images": "./images/",
	"audio": "G:/game/indian/anim/logo"
},
"bones": [
	{ "name": "root" },
	{ "name": "bone", "parent": "root", "x": 15.72, "y": -97.37 },
	{ "name": "bg", "parent": "bone", "x": 2.77, "y": 87.29 },
	{ "name": "andar", "parent": "bone", "x": -23.3, "y": 128.77 },
	{ "name": "bahar", "parent": "bone", "x": 40.68, "y": 54.9 },
	{ "name": "bg2", "parent": "bg", "x": 124.82, "y": 7.9 },
	{ "name": "canh1", "parent": "bg2", "length": 32.38, "rotation": 48.79, "x": 5.14, "y": 3.16 },
	{ "name": "canh1b", "parent": "canh1", "length": 32.38, "x": 32.38 },
	{ "name": "canh1c", "parent": "canh1b", "length": 32.38, "x": 32.38 },
	{ "name": "chip2", "parent": "bone", "x": -9.87, "y": 194.34 },
	{ "name": "labai", "parent": "bone", "length": 35.41, "rotation": 80.15, "x": -139.04, "y": 141.8 },
	{ "name": "labai2", "parent": "labai", "length": 35.41, "x": 35.41 },
	{ "name": "labai3", "parent": "labai2", "length": 35.41, "x": 35.41 },
	{ "name": "chip", "parent": "bone", "x": -40.29, "y": 263.46 },
	{ "name": "bg3", "parent": "bg", "x": -182.88, "y": -9.87, "scaleX": -1 },
	{ "name": "canh3", "parent": "bg3", "length": 32.38, "rotation": 48.79, "x": 5.14, "y": 3.16 },
	{ "name": "canh1b2", "parent": "canh3", "length": 32.38, "x": 32.38 },
	{ "name": "canh1c2", "parent": "canh1b2", "length": 32.38, "x": 32.38 },
	{ "name": "ef", "parent": "andar", "x": -26.73, "y": -16.76 },
	{ "name": "ef2", "parent": "andar", "x": 147.13, "y": 27.12 },
	{ "name": "ef3", "parent": "andar", "x": -127.17, "y": -27.31 },
	{ "name": "ef4", "parent": "bahar", "x": -106.76, "y": -19.7 },
	{ "name": "ef5", "parent": "bahar", "x": 110.99, "y": -15.48 },
	{ "name": "ef6", "parent": "bahar", "x": 12.67, "y": 26.72 }
],
"slots": [
	{ "name": "bg", "bone": "bg", "attachment": "bg" },
	{ "name": "canh1", "bone": "canh1", "attachment": "canh1" },
	{ "name": "canh3", "bone": "canh3", "attachment": "canh1" },
	{ "name": "labai", "bone": "labai", "attachment": "labai" },
	{ "name": "chip", "bone": "chip", "attachment": "chip" },
	{ "name": "chip2", "bone": "chip2", "attachment": "chip2" },
	{ "name": "andar", "bone": "andar", "attachment": "andar" },
	{ "name": "bahar", "bone": "bahar", "attachment": "bahar" },
	{ "name": "ef", "bone": "ef", "attachment": "ef", "blend": "additive" },
	{ "name": "ef2", "bone": "ef2", "attachment": "ef", "blend": "additive" },
	{ "name": "ef3", "bone": "ef3", "attachment": "ef", "blend": "additive" },
	{ "name": "ef4", "bone": "ef4", "attachment": "ef", "blend": "additive" },
	{ "name": "ef5", "bone": "ef5", "attachment": "ef", "blend": "additive" },
	{ "name": "ef6", "bone": "ef6", "attachment": "ef", "blend": "additive" }
],
"skins": [
	{
		"name": "default",
		"attachments": {
			"andar": {
				"andar": { "x": -5.47, "y": -7.52, "width": 379, "height": 116 }
			},
			"bahar": {
				"bahar": { "x": -1.46, "y": -3.66, "width": 335, "height": 112 }
			},
			"bg": {
				"bg": { "x": -9.04, "y": -0.05, "width": 454, "height": 144 }
			},
			"canh1": {
				"canh1": {
					"type": "mesh",
					"uvs": [ 0.80648, 0.0428, 0.95703, 0.41352, 0.93715, 0.69397, 0.82876, 0.86499, 0.57411, 0.9849, 0.14972, 0.9855, 0, 0.93992, 0, 0.9349, 0.07936, 0.82656, 0.30166, 0.77025, 0.36202, 0.70678, 0.40163, 0.52168, 0.52401, 0.31413, 0.50892, 0.12326, 0.70618, 0.02054 ],
					"triangles": [ 0, 12, 13, 0, 13, 14, 12, 0, 1, 1, 11, 12, 2, 11, 1, 10, 11, 2, 3, 10, 2, 5, 6, 7, 4, 10, 3, 9, 10, 4, 5, 8, 9, 5, 9, 4, 5, 7, 8 ],
					"vertices": [ 1, 8, 63.25, 31.73, 1, 2, 7, 68.55, -12.19, 0.00994, 8, 36.17, -12.19, 0.99006, 3, 6, 71.54, -35.26, 0.00436, 7, 39.17, -35.26, 0.54229, 8, 6.79, -35.26, 0.45335, 3, 6, 47.22, -42.01, 0.10607, 7, 14.84, -42.01, 0.7721, 8, -17.54, -42.01, 0.12184, 3, 6, 18.28, -33.16, 0.54048, 7, -14.1, -33.16, 0.45693, 8, -46.48, -33.16, 0.00259, 1, 6, -10.02, -0.97, 1, 1, 6, -15.42, 14.4, 1, 1, 6, -14.92, 14.84, 1, 1, 6, 1.2, 18.3, 1, 1, 6, 21.63, 6.35, 1, 2, 6, 31.99, 7.32, 0.33947, 7, -0.38, 7.32, 0.66053, 2, 7, 20.77, 20.53, 0.83116, 8, -11.6, 20.53, 0.16884, 2, 7, 49.68, 29.42, 0.04532, 8, 17.31, 29.42, 0.95468, 1, 8, 35.4, 47.29, 1, 1, 8, 58.8, 41.3, 1 ],
					"hull": 15,
					"edges": [ 0, 28, 0, 2, 2, 4, 4, 6, 6, 8, 8, 10, 10, 12, 12, 14, 14, 16, 16, 18, 18, 20, 20, 22, 22, 24, 24, 26, 26, 28 ],
					"width": 101,
					"height": 133
				}
			},
			"canh3": {
				"canh1": {
					"type": "mesh",
					"uvs": [ 0.80648, 0.0428, 0.95703, 0.41352, 0.93715, 0.69397, 0.82876, 0.86499, 0.57411, 0.9849, 0.14972, 0.9855, 0, 0.93992, 0, 0.9349, 0.07936, 0.82656, 0.30166, 0.77025, 0.36202, 0.70678, 0.40163, 0.52168, 0.52401, 0.31413, 0.50892, 0.12326, 0.70618, 0.02054 ],
					"triangles": [ 0, 12, 13, 0, 13, 14, 12, 0, 1, 1, 11, 12, 2, 11, 1, 10, 11, 2, 3, 10, 2, 5, 6, 7, 4, 10, 3, 9, 10, 4, 5, 8, 9, 5, 9, 4, 5, 7, 8 ],
					"vertices": [ 1, 17, 63.25, 31.73, 1, 2, 16, 68.55, -12.19, 0.00994, 17, 36.17, -12.19, 0.99006, 3, 15, 71.54, -35.26, 0.00436, 16, 39.17, -35.26, 0.54229, 17, 6.79, -35.26, 0.45335, 3, 15, 47.22, -42.01, 0.10607, 16, 14.84, -42.01, 0.7721, 17, -17.54, -42.01, 0.12184, 3, 15, 18.28, -33.16, 0.54048, 16, -14.1, -33.16, 0.45693, 17, -46.48, -33.16, 0.00259, 1, 15, -10.02, -0.97, 1, 1, 15, -15.42, 14.4, 1, 1, 15, -14.92, 14.84, 1, 1, 15, 1.2, 18.3, 1, 1, 15, 21.63, 6.35, 1, 2, 15, 31.99, 7.32, 0.33947, 16, -0.38, 7.32, 0.66053, 2, 16, 20.77, 20.53, 0.83116, 17, -11.6, 20.53, 0.16884, 2, 16, 49.68, 29.42, 0.04532, 17, 17.31, 29.42, 0.95468, 1, 17, 35.4, 47.29, 1, 1, 17, 58.8, 41.3, 1 ],
					"hull": 15,
					"edges": [ 0, 28, 0, 2, 2, 4, 4, 6, 6, 8, 8, 10, 10, 12, 12, 14, 14, 16, 16, 18, 18, 20, 20, 22, 22, 24, 24, 26, 26, 28 ],
					"width": 101,
					"height": 133
				}
			},
			"chip": {
				"chip": { "x": 2.01, "y": -2.21, "width": 44, "height": 44 }
			},
			"chip2": {
				"chip2": { "x": -1.9, "y": 2.91, "width": 161, "height": 128 }
			},
			"ef": {
				"ef": { "x": -4.24, "y": -0.61, "width": 128, "height": 120 }
			},
			"ef2": {
				"ef": { "x": -4.24, "y": -0.61, "width": 128, "height": 120 }
			},
			"ef3": {
				"ef": { "x": -4.24, "y": -0.61, "width": 128, "height": 120 }
			},
			"ef4": {
				"ef": { "x": -4.24, "y": -0.61, "width": 128, "height": 120 }
			},
			"ef5": {
				"ef": { "x": -4.24, "y": -0.61, "width": 128, "height": 120 }
			},
			"ef6": {
				"ef": { "x": -4.24, "y": -0.61, "width": 128, "height": 120 }
			},
			"labai": {
				"labai": {
					"type": "mesh",
					"uvs": [ 0.45509, 0, 0.95994, 0.09534, 1, 0.29838, 1, 0.39678, 0.96126, 0.71077, 0.76699, 0.92625, 0.52221, 0.89503, 0.38219, 0.93207, 0.11191, 1, 0.09933, 1, 0.10087, 0.88744, 0.1811, 0.68584, 0.15185, 0.53903, 0, 0.27629, 0.01553, 0.20361, 0.286, 0.16159, 0.32951, 0.04047, 0.3993, 0 ],
					"triangles": [ 0, 1, 2, 15, 13, 14, 12, 13, 15, 6, 7, 11, 0, 2, 3, 0, 3, 15, 4, 6, 3, 5, 6, 4, 16, 0, 15, 15, 6, 12, 12, 6, 11, 10, 11, 7, 0, 16, 17, 15, 3, 6, 8, 9, 10, 7, 8, 10 ],
					"vertices": [ 2, 11, 91.03, 28.47, 0.02335, 12, 55.61, 28.47, 0.97665, 3, 10, 124.18, -48.27, 0.00245, 11, 88.77, -48.27, 0.12448, 12, 53.35, -48.27, 0.87307, 3, 10, 92.99, -59.74, 0.05985, 11, 57.58, -59.74, 0.32243, 12, 22.17, -59.74, 0.61772, 3, 10, 77.38, -62.45, 0.13677, 11, 41.97, -62.45, 0.43994, 12, 6.56, -62.45, 0.42329, 3, 10, 26.59, -65.41, 0.6179, 11, -8.82, -65.41, 0.36027, 12, -44.24, -65.41, 0.02183, 2, 10, -12.54, -42.82, 0.92908, 11, -47.96, -42.82, 0.07092, 2, 10, -13.83, -6.03, 0.99938, 11, -49.24, -6.03, 6.2E-4, 1, 10, -23.27, 13.51, 1, 1, 10, -40.93, 51.32, 1, 1, 10, -41.26, 53.16, 1, 2, 10, -23.36, 56.04, 0.99592, 11, -58.77, 56.04, 0.00408, 3, 10, 10.66, 49.81, 0.8244, 11, -24.75, 49.81, 0.1676, 12, -60.16, 49.81, 0.008, 3, 10, 33.21, 58.15, 0.41099, 11, -2.21, 58.15, 0.49146, 12, -37.62, 58.15, 0.09755, 3, 10, 71.01, 87.67, 0.05091, 11, 35.6, 87.67, 0.60089, 12, 0.19, 87.67, 0.3482, 3, 10, 82.94, 87.39, 0.04219, 11, 47.53, 87.39, 0.59403, 12, 12.11, 87.39, 0.36378, 3, 10, 96.5, 48.85, 0.00885, 11, 61.08, 48.85, 0.30238, 12, 25.67, 48.85, 0.68877, 2, 11, 81.4, 45.79, 0.08179, 12, 45.99, 45.79, 0.91821, 2, 11, 89.6, 36.66, 0.04135, 12, 54.19, 36.66, 0.95865 ],
					"hull": 18,
					"edges": [ 0, 34, 0, 2, 2, 4, 4, 6, 6, 8, 8, 10, 10, 12, 12, 14, 14, 16, 16, 18, 18, 20, 20, 22, 22, 24, 24, 26, 26, 28, 28, 30, 30, 32, 32, 34 ],
					"width": 149,
					"height": 161
				}
			}
		}
	}
],
"animations": {
	"animation": {
		"bones": {
			"canh1": {
				"rotate": [
					{ "curve": 0.25, "c3": 0.75 },
					{ "time": 0.6667, "angle": 9.56, "curve": 0.25, "c3": 0.75 },
					{ "time": 1.3333 }
				]
			},
			"canh1b": {
				"rotate": [
					{ "angle": 1.76, "curve": 0.379, "c2": 0.6, "c3": 0.724 },
					{ "time": 0.1667, "curve": 0.25, "c3": 0.75 },
					{ "time": 0.8333, "angle": 9.56, "curve": 0.242, "c3": 0.667, "c4": 0.67 },
					{ "time": 1.3333, "angle": 1.76 }
				]
			},
			"canh1c": {
				"rotate": [
					{ "angle": 4.78, "curve": 0.375, "c2": 0.5, "c3": 0.75 },
					{ "time": 0.3333, "curve": 0.25, "c3": 0.75 },
					{ "time": 1, "angle": 9.56, "curve": 0.25, "c3": 0.625, "c4": 0.5 },
					{ "time": 1.3333, "angle": 4.78 }
				]
			},
			"canh1c2": {
				"rotate": [
					{ "angle": 4.78, "curve": 0.375, "c2": 0.5, "c3": 0.75 },
					{ "time": 0.3333, "curve": 0.25, "c3": 0.75 },
					{ "time": 1, "angle": 9.56, "curve": 0.25, "c3": 0.625, "c4": 0.5 },
					{ "time": 1.3333, "angle": 4.78 }
				]
			},
			"canh1b2": {
				"rotate": [
					{ "angle": 1.76, "curve": 0.379, "c2": 0.6, "c3": 0.724 },
					{ "time": 0.1667, "curve": 0.25, "c3": 0.75 },
					{ "time": 0.8333, "angle": 9.56, "curve": 0.242, "c3": 0.667, "c4": 0.67 },
					{ "time": 1.3333, "angle": 1.76 }
				]
			},
			"canh3": {
				"rotate": [
					{ "curve": 0.25, "c3": 0.75 },
					{ "time": 0.6667, "angle": 9.56, "curve": 0.25, "c3": 0.75 },
					{ "time": 1.3333 }
				]
			},
			"labai": {
				"rotate": [
					{ "angle": 2.42, "curve": 0.375, "c2": 0.5, "c3": 0.75 },
					{ "time": 0.3333, "curve": 0.25, "c3": 0.75 },
					{ "time": 1, "angle": 4.85, "curve": 0.25, "c3": 0.625, "c4": 0.5 },
					{ "time": 1.3333, "angle": 2.42 }
				]
			},
			"labai2": {
				"rotate": [
					{ "angle": 3.95, "curve": 0.333, "c2": 0.33, "c3": 0.758 },
					{ "time": 0.5, "curve": 0.25, "c3": 0.75 },
					{ "time": 1.1667, "angle": 4.85, "curve": 0.276, "c3": 0.621, "c4": 0.4 },
					{ "time": 1.3333, "angle": 3.95 }
				]
			},
			"labai3": {
				"rotate": [
					{ "angle": 4.85, "curve": 0.25, "c3": 0.75 },
					{ "time": 0.6667, "curve": 0.25, "c3": 0.75 },
					{ "time": 1.3333, "angle": 4.85 }
				]
			},
			"chip2": {
				"translate": [
					{ "curve": 0.25, "c3": 0.75 },
					{ "time": 0.6667, "x": -8.29, "y": -9.08, "curve": 0.25, "c3": 0.75 },
					{ "time": 1.3333 }
				]
			},
			"chip": {
				"translate": [
					{ "curve": 0.25, "c3": 0.75 },
					{ "time": 0.6667, "y": -7.11, "curve": 0.25, "c3": 0.75 },
					{ "time": 1.3333 }
				]
			},
			"andar": {
				"scale": [
					{ "curve": 0.25, "c3": 0.75 },
					{ "time": 0.6667, "x": 1.057, "y": 1.057, "curve": 0.25, "c3": 0.75 },
					{ "time": 1.3333 }
				]
			},
			"bahar": {
				"scale": [
					{ "x": 1.072, "y": 1.072, "curve": 0.333, "c2": 0.33, "c3": 0.758 },
					{ "time": 0.5, "curve": 0.25, "c3": 0.75 },
					{ "time": 1.1667, "x": 1.089, "y": 1.089, "curve": 0.276, "c3": 0.621, "c4": 0.4 },
					{ "time": 1.3333, "x": 1.072, "y": 1.072 }
				]
			},
			"ef": {
				"scale": [
					{ "x": 0, "y": 0 },
					{ "time": 0.2333 },
					{ "time": 0.5, "x": 0, "y": 0 }
				]
			},
			"ef2": {
				"scale": [
					{ "x": 0, "y": 0, "curve": "stepped" },
					{ "time": 0.1667, "x": 0, "y": 0 },
					{ "time": 0.4 },
					{ "time": 0.6667, "x": 0, "y": 0 }
				]
			},
			"ef3": {
				"scale": [
					{ "x": 0, "y": 0, "curve": "stepped" },
					{ "time": 0.3333, "x": 0, "y": 0 },
					{ "time": 0.5667 },
					{ "time": 0.8333, "x": 0, "y": 0 }
				]
			},
			"ef4": {
				"scale": [
					{ "x": 0, "y": 0, "curve": "stepped" },
					{ "time": 0.5, "x": 0, "y": 0 },
					{ "time": 0.7333 },
					{ "time": 1, "x": 0, "y": 0 }
				]
			},
			"ef5": {
				"scale": [
					{ "x": 0, "y": 0, "curve": "stepped" },
					{ "time": 0.6667, "x": 0, "y": 0 },
					{ "time": 0.9 },
					{ "time": 1.1667, "x": 0, "y": 0 }
				]
			},
			"ef6": {
				"scale": [
					{ "x": 0, "y": 0, "curve": "stepped" },
					{ "time": 0.8333, "x": 0, "y": 0 },
					{ "time": 1.0667 },
					{ "time": 1.3333, "x": 0, "y": 0 }
				]
			}
		}
	}
}
}